{
    "name": "Global Information",
    "numberOfRequests": {
        "total": 11507,
        "ok": 10207,
        "ko": 1300
    },
    "minResponseTime": {
        "total": 19,
        "ok": 19,
        "ko": 27
    },
    "maxResponseTime": {
        "total": 43580,
        "ok": 43580,
        "ko": 7508
    },
    "meanResponseTime": {
        "total": 1262,
        "ok": 1385,
        "ko": 297
    },
    "standardDeviation": {
        "total": 3828,
        "ok": 4043,
        "ko": 572
    },
    "percentiles1": {
        "total": 121,
        "ok": 127,
        "ko": 100
    },
    "percentiles2": {
        "total": 465,
        "ok": 515,
        "ko": 295
    },
    "percentiles3": {
        "total": 6435,
        "ok": 6929,
        "ko": 1459
    },
    "percentiles4": {
        "total": 22965,
        "ok": 25319,
        "ko": 2251
    },
    "group1": {
        "name": "t < 800 ms",
        "count": 8141,
        "percentage": 71
    },
    "group2": {
        "name": "800 ms < t < 1200 ms",
        "count": 426,
        "percentage": 4
    },
    "group3": {
        "name": "t > 1200 ms",
        "count": 1640,
        "percentage": 14
    },
    "group4": {
        "name": "failed",
        "count": 1300,
        "percentage": 11
    },
    "meanNumberOfRequestsPerSecond": {
        "total": 96.69747899159664,
        "ok": 85.77310924369748,
        "ko": 10.92436974789916
    }
}