{
  "type": "GROUP",
"name": "Global Information",
"path": "",
"pathFormatted": "group_missing-name-b06d1",
"stats": {
    "name": "Global Information",
    "numberOfRequests": {
        "total": 24200,
        "ok": 23000,
        "ko": 1200
    },
    "minResponseTime": {
        "total": 17,
        "ok": 17,
        "ko": 24
    },
    "maxResponseTime": {
        "total": 49915,
        "ok": 49915,
        "ko": 12526
    },
    "meanResponseTime": {
        "total": 1240,
        "ok": 1197,
        "ko": 2060
    },
    "standardDeviation": {
        "total": 2370,
        "ok": 2357,
        "ko": 2474
    },
    "percentiles1": {
        "total": 470,
        "ok": 464,
        "ko": 894
    },
    "percentiles2": {
        "total": 1021,
        "ok": 981,
        "ko": 3010
    },
    "percentiles3": {
        "total": 6084,
        "ok": 5709,
        "ko": 7184
    },
    "percentiles4": {
        "total": 11308,
        "ok": 11564,
        "ko": 7535
    },
    "group1": {
        "name": "t < 800 ms",
        "count": 16058,
        "percentage": 66
    },
    "group2": {
        "name": "800 ms < t < 1200 ms",
        "count": 2346,
        "percentage": 10
    },
    "group3": {
        "name": "t > 1200 ms",
        "count": 4596,
        "percentage": 19
    },
    "group4": {
        "name": "failed",
        "count": 1200,
        "percentage": 5
    },
    "meanNumberOfRequestsPerSecond": {
        "total": 136.72316384180792,
        "ok": 129.94350282485877,
        "ko": 6.779661016949152
    }
},
"contents": {
"req_gerar-token-b1626": {
        "type": "REQUEST",
        "name": "Gerar Token",
"path": "Gerar Token",
"pathFormatted": "req_gerar-token-b1626",
"stats": {
    "name": "Gerar Token",
    "numberOfRequests": {
        "total": 200,
        "ok": 0,
        "ko": 200
    },
    "minResponseTime": {
        "total": 6200,
        "ok": 0,
        "ko": 6200
    },
    "maxResponseTime": {
        "total": 8391,
        "ok": 0,
        "ko": 8391
    },
    "meanResponseTime": {
        "total": 6819,
        "ok": 0,
        "ko": 6819
    },
    "standardDeviation": {
        "total": 447,
        "ok": 0,
        "ko": 447
    },
    "percentiles1": {
        "total": 6833,
        "ok": 0,
        "ko": 6833
    },
    "percentiles2": {
        "total": 7197,
        "ok": 0,
        "ko": 7197
    },
    "percentiles3": {
        "total": 7314,
        "ok": 0,
        "ko": 7314
    },
    "percentiles4": {
        "total": 7793,
        "ok": 0,
        "ko": 7793
    },
    "group1": {
        "name": "t < 800 ms",
        "count": 0,
        "percentage": 0
    },
    "group2": {
        "name": "800 ms < t < 1200 ms",
        "count": 0,
        "percentage": 0
    },
    "group3": {
        "name": "t > 1200 ms",
        "count": 0,
        "percentage": 0
    },
    "group4": {
        "name": "failed",
        "count": 200,
        "percentage": 100
    },
    "meanNumberOfRequestsPerSecond": {
        "total": 1.1299435028248588,
        "ok": 0,
        "ko": 1.1299435028248588
    }
}
    },"req_request-0-684d2": {
        "type": "REQUEST",
        "name": "request_0",
"path": "request_0",
"pathFormatted": "req_request-0-684d2",
"stats": {
    "name": "request_0",
    "numberOfRequests": {
        "total": 200,
        "ok": 200,
        "ko": 0
    },
    "minResponseTime": {
        "total": 5044,
        "ok": 5044,
        "ko": 0
    },
    "maxResponseTime": {
        "total": 13061,
        "ok": 13061,
        "ko": 0
    },
    "meanResponseTime": {
        "total": 7997,
        "ok": 7997,
        "ko": 0
    },
    "standardDeviation": {
        "total": 1685,
        "ok": 1685,
        "ko": 0
    },
    "percentiles1": {
        "total": 7646,
        "ok": 7646,
        "ko": 0
    },
    "percentiles2": {
        "total": 9444,
        "ok": 9444,
        "ko": 0
    },
    "percentiles3": {
        "total": 10601,
        "ok": 10601,
        "ko": 0
    },
    "percentiles4": {
        "total": 12291,
        "ok": 12291,
        "ko": 0
    },
    "group1": {
        "name": "t < 800 ms",
        "count": 0,
        "percentage": 0
    },
    "group2": {
        "name": "800 ms < t < 1200 ms",
        "count": 0,
        "percentage": 0
    },
    "group3": {
        "name": "t > 1200 ms",
        "count": 200,
        "percentage": 100
    },
    "group4": {
        "name": "failed",
        "count": 0,
        "percentage": 0
    },
    "meanNumberOfRequestsPerSecond": {
        "total": 1.1299435028248588,
        "ok": 1.1299435028248588,
        "ko": 0
    }
}
    },"req_request-1-46da4": {
        "type": "REQUEST",
        "name": "request_1",
"path": "request_1",
"pathFormatted": "req_request-1-46da4",
"stats": {
    "name": "request_1",
    "numberOfRequests": {
        "total": 200,
        "ok": 200,
        "ko": 0
    },
    "minResponseTime": {
        "total": 26,
        "ok": 26,
        "ko": 0
    },
    "maxResponseTime": {
        "total": 4345,
        "ok": 4345,
        "ko": 0
    },
    "meanResponseTime": {
        "total": 809,
        "ok": 809,
        "ko": 0
    },
    "standardDeviation": {
        "total": 588,
        "ok": 588,
        "ko": 0
    },
    "percentiles1": {
        "total": 708,
        "ok": 708,
        "ko": 0
    },
    "percentiles2": {
        "total": 1128,
        "ok": 1128,
        "ko": 0
    },
    "percentiles3": {
        "total": 1958,
        "ok": 1958,
        "ko": 0
    },
    "percentiles4": {
        "total": 2364,
        "ok": 2364,
        "ko": 0
    },
    "group1": {
        "name": "t < 800 ms",
        "count": 106,
        "percentage": 53
    },
    "group2": {
        "name": "800 ms < t < 1200 ms",
        "count": 52,
        "percentage": 26
    },
    "group3": {
        "name": "t > 1200 ms",
        "count": 42,
        "percentage": 21
    },
    "group4": {
        "name": "failed",
        "count": 0,
        "percentage": 0
    },
    "meanNumberOfRequestsPerSecond": {
        "total": 1.1299435028248588,
        "ok": 1.1299435028248588,
        "ko": 0
    }
}
    },"req_request-3-d0973": {
        "type": "REQUEST",
        "name": "request_3",
"path": "request_3",
"pathFormatted": "req_request-3-d0973",
"stats": {
    "name": "request_3",
    "numberOfRequests": {
        "total": 200,
        "ok": 200,
        "ko": 0
    },
    "minResponseTime": {
        "total": 76,
        "ok": 76,
        "ko": 0
    },
    "maxResponseTime": {
        "total": 5549,
        "ok": 5549,
        "ko": 0
    },
    "meanResponseTime": {
        "total": 2056,
        "ok": 2056,
        "ko": 0
    },
    "standardDeviation": {
        "total": 1251,
        "ok": 1251,
        "ko": 0
    },
    "percentiles1": {
        "total": 1948,
        "ok": 1948,
        "ko": 0
    },
    "percentiles2": {
        "total": 2787,
        "ok": 2787,
        "ko": 0
    },
    "percentiles3": {
        "total": 4172,
        "ok": 4172,
        "ko": 0
    },
    "percentiles4": {
        "total": 5473,
        "ok": 5473,
        "ko": 0
    },
    "group1": {
        "name": "t < 800 ms",
        "count": 55,
        "percentage": 28
    },
    "group2": {
        "name": "800 ms < t < 1200 ms",
        "count": 10,
        "percentage": 5
    },
    "group3": {
        "name": "t > 1200 ms",
        "count": 135,
        "percentage": 68
    },
    "group4": {
        "name": "failed",
        "count": 0,
        "percentage": 0
    },
    "meanNumberOfRequestsPerSecond": {
        "total": 1.1299435028248588,
        "ok": 1.1299435028248588,
        "ko": 0
    }
}
    },"req_request-4-e7d1b": {
        "type": "REQUEST",
        "name": "request_4",
"path": "request_4",
"pathFormatted": "req_request-4-e7d1b",
"stats": {
    "name": "request_4",
    "numberOfRequests": {
        "total": 200,
        "ok": 200,
        "ko": 0
    },
    "minResponseTime": {
        "total": 76,
        "ok": 76,
        "ko": 0
    },
    "maxResponseTime": {
        "total": 5550,
        "ok": 5550,
        "ko": 0
    },
    "meanResponseTime": {
        "total": 2099,
        "ok": 2099,
        "ko": 0
    },
    "standardDeviation": {
        "total": 1297,
        "ok": 1297,
        "ko": 0
    },
    "percentiles1": {
        "total": 1974,
        "ok": 1974,
        "ko": 0
    },
    "percentiles2": {
        "total": 3095,
        "ok": 3095,
        "ko": 0
    },
    "percentiles3": {
        "total": 4172,
        "ok": 4172,
        "ko": 0
    },
    "percentiles4": {
        "total": 5541,
        "ok": 5541,
        "ko": 0
    },
    "group1": {
        "name": "t < 800 ms",
        "count": 54,
        "percentage": 27
    },
    "group2": {
        "name": "800 ms < t < 1200 ms",
        "count": 11,
        "percentage": 6
    },
    "group3": {
        "name": "t > 1200 ms",
        "count": 135,
        "percentage": 68
    },
    "group4": {
        "name": "failed",
        "count": 0,
        "percentage": 0
    },
    "meanNumberOfRequestsPerSecond": {
        "total": 1.1299435028248588,
        "ok": 1.1299435028248588,
        "ko": 0
    }
}
    },"req_req-login-ifram-d5163": {
        "type": "REQUEST",
        "name": "req_login_iframe",
"path": "req_login_iframe",
"pathFormatted": "req_req-login-ifram-d5163",
"stats": {
    "name": "req_login_iframe",
    "numberOfRequests": {
        "total": 400,
        "ok": 0,
        "ko": 400
    },
    "minResponseTime": {
        "total": 24,
        "ok": 0,
        "ko": 24
    },
    "maxResponseTime": {
        "total": 5864,
        "ok": 0,
        "ko": 5864
    },
    "meanResponseTime": {
        "total": 1420,
        "ok": 0,
        "ko": 1420
    },
    "standardDeviation": {
        "total": 1158,
        "ok": 0,
        "ko": 1158
    },
    "percentiles1": {
        "total": 1037,
        "ok": 0,
        "ko": 1037
    },
    "percentiles2": {
        "total": 2109,
        "ok": 0,
        "ko": 2109
    },
    "percentiles3": {
        "total": 3887,
        "ok": 0,
        "ko": 3887
    },
    "percentiles4": {
        "total": 4748,
        "ok": 0,
        "ko": 4748
    },
    "group1": {
        "name": "t < 800 ms",
        "count": 0,
        "percentage": 0
    },
    "group2": {
        "name": "800 ms < t < 1200 ms",
        "count": 0,
        "percentage": 0
    },
    "group3": {
        "name": "t > 1200 ms",
        "count": 0,
        "percentage": 0
    },
    "group4": {
        "name": "failed",
        "count": 400,
        "percentage": 100
    },
    "meanNumberOfRequestsPerSecond": {
        "total": 2.2598870056497176,
        "ok": 0,
        "ko": 2.2598870056497176
    }
}
    },"req_request-8-ef0c8": {
        "type": "REQUEST",
        "name": "request_8",
"path": "request_8",
"pathFormatted": "req_request-8-ef0c8",
"stats": {
    "name": "request_8",
    "numberOfRequests": {
        "total": 200,
        "ok": 200,
        "ko": 0
    },
    "minResponseTime": {
        "total": 18,
        "ok": 18,
        "ko": 0
    },
    "maxResponseTime": {
        "total": 5093,
        "ok": 5093,
        "ko": 0
    },
    "meanResponseTime": {
        "total": 2179,
        "ok": 2179,
        "ko": 0
    },
    "standardDeviation": {
        "total": 1103,
        "ok": 1103,
        "ko": 0
    },
    "percentiles1": {
        "total": 2006,
        "ok": 2006,
        "ko": 0
    },
    "percentiles2": {
        "total": 2835,
        "ok": 2835,
        "ko": 0
    },
    "percentiles3": {
        "total": 4620,
        "ok": 4620,
        "ko": 0
    },
    "percentiles4": {
        "total": 4949,
        "ok": 4949,
        "ko": 0
    },
    "group1": {
        "name": "t < 800 ms",
        "count": 21,
        "percentage": 11
    },
    "group2": {
        "name": "800 ms < t < 1200 ms",
        "count": 7,
        "percentage": 4
    },
    "group3": {
        "name": "t > 1200 ms",
        "count": 172,
        "percentage": 86
    },
    "group4": {
        "name": "failed",
        "count": 0,
        "percentage": 0
    },
    "meanNumberOfRequestsPerSecond": {
        "total": 1.1299435028248588,
        "ok": 1.1299435028248588,
        "ko": 0
    }
}
    },"req_request-13-5cca6": {
        "type": "REQUEST",
        "name": "request_13",
"path": "request_13",
"pathFormatted": "req_request-13-5cca6",
"stats": {
    "name": "request_13",
    "numberOfRequests": {
        "total": 200,
        "ok": 0,
        "ko": 200
    },
    "minResponseTime": {
        "total": 81,
        "ok": 0,
        "ko": 81
    },
    "maxResponseTime": {
        "total": 12526,
        "ok": 0,
        "ko": 12526
    },
    "meanResponseTime": {
        "total": 1278,
        "ok": 0,
        "ko": 1278
    },
    "standardDeviation": {
        "total": 1913,
        "ok": 0,
        "ko": 1913
    },
    "percentiles1": {
        "total": 391,
        "ok": 0,
        "ko": 391
    },
    "percentiles2": {
        "total": 1392,
        "ok": 0,
        "ko": 1392
    },
    "percentiles3": {
        "total": 4973,
        "ok": 0,
        "ko": 4973
    },
    "percentiles4": {
        "total": 9580,
        "ok": 0,
        "ko": 9580
    },
    "group1": {
        "name": "t < 800 ms",
        "count": 0,
        "percentage": 0
    },
    "group2": {
        "name": "800 ms < t < 1200 ms",
        "count": 0,
        "percentage": 0
    },
    "group3": {
        "name": "t > 1200 ms",
        "count": 0,
        "percentage": 0
    },
    "group4": {
        "name": "failed",
        "count": 200,
        "percentage": 100
    },
    "meanNumberOfRequestsPerSecond": {
        "total": 1.1299435028248588,
        "ok": 0,
        "ko": 1.1299435028248588
    }
}
    },"req_req-auth-4422a": {
        "type": "REQUEST",
        "name": "req_auth",
"path": "req_auth",
"pathFormatted": "req_req-auth-4422a",
"stats": {
    "name": "req_auth",
    "numberOfRequests": {
        "total": 200,
        "ok": 0,
        "ko": 200
    },
    "minResponseTime": {
        "total": 82,
        "ok": 0,
        "ko": 82
    },
    "maxResponseTime": {
        "total": 8018,
        "ok": 0,
        "ko": 8018
    },
    "meanResponseTime": {
        "total": 1079,
        "ok": 0,
        "ko": 1079
    },
    "standardDeviation": {
        "total": 1400,
        "ok": 0,
        "ko": 1400
    },
    "percentiles1": {
        "total": 390,
        "ok": 0,
        "ko": 390
    },
    "percentiles2": {
        "total": 1374,
        "ok": 0,
        "ko": 1374
    },
    "percentiles3": {
        "total": 4679,
        "ok": 0,
        "ko": 4679
    },
    "percentiles4": {
        "total": 5030,
        "ok": 0,
        "ko": 5030
    },
    "group1": {
        "name": "t < 800 ms",
        "count": 0,
        "percentage": 0
    },
    "group2": {
        "name": "800 ms < t < 1200 ms",
        "count": 0,
        "percentage": 0
    },
    "group3": {
        "name": "t > 1200 ms",
        "count": 0,
        "percentage": 0
    },
    "group4": {
        "name": "failed",
        "count": 200,
        "percentage": 100
    },
    "meanNumberOfRequestsPerSecond": {
        "total": 1.1299435028248588,
        "ok": 0,
        "ko": 1.1299435028248588
    }
}
    },"req_req-duvidas-3bb5f": {
        "type": "REQUEST",
        "name": "req_duvidas",
"path": "req_duvidas",
"pathFormatted": "req_req-duvidas-3bb5f",
"stats": {
    "name": "req_duvidas",
    "numberOfRequests": {
        "total": 2000,
        "ok": 2000,
        "ko": 0
    },
    "minResponseTime": {
        "total": 22,
        "ok": 22,
        "ko": 0
    },
    "maxResponseTime": {
        "total": 41854,
        "ok": 41854,
        "ko": 0
    },
    "meanResponseTime": {
        "total": 1871,
        "ok": 1871,
        "ko": 0
    },
    "standardDeviation": {
        "total": 3351,
        "ok": 3351,
        "ko": 0
    },
    "percentiles1": {
        "total": 582,
        "ok": 582,
        "ko": 0
    },
    "percentiles2": {
        "total": 1332,
        "ok": 1332,
        "ko": 0
    },
    "percentiles3": {
        "total": 10147,
        "ok": 10147,
        "ko": 0
    },
    "percentiles4": {
        "total": 13064,
        "ok": 13064,
        "ko": 0
    },
    "group1": {
        "name": "t < 800 ms",
        "count": 1226,
        "percentage": 61
    },
    "group2": {
        "name": "800 ms < t < 1200 ms",
        "count": 219,
        "percentage": 11
    },
    "group3": {
        "name": "t > 1200 ms",
        "count": 555,
        "percentage": 28
    },
    "group4": {
        "name": "failed",
        "count": 0,
        "percentage": 0
    },
    "meanNumberOfRequestsPerSecond": {
        "total": 11.299435028248588,
        "ok": 11.299435028248588,
        "ko": 0
    }
}
    },"req_req-listar-filh-6ac77": {
        "type": "REQUEST",
        "name": "req_listar_filhos_ativos",
"path": "req_listar_filhos_ativos",
"pathFormatted": "req_req-listar-filh-6ac77",
"stats": {
    "name": "req_listar_filhos_ativos",
    "numberOfRequests": {
        "total": 6200,
        "ok": 6200,
        "ko": 0
    },
    "minResponseTime": {
        "total": 20,
        "ok": 20,
        "ko": 0
    },
    "maxResponseTime": {
        "total": 49915,
        "ok": 49915,
        "ko": 0
    },
    "meanResponseTime": {
        "total": 1535,
        "ok": 1535,
        "ko": 0
    },
    "standardDeviation": {
        "total": 3009,
        "ok": 3009,
        "ko": 0
    },
    "percentiles1": {
        "total": 552,
        "ok": 552,
        "ko": 0
    },
    "percentiles2": {
        "total": 1161,
        "ok": 1161,
        "ko": 0
    },
    "percentiles3": {
        "total": 7556,
        "ok": 7556,
        "ko": 0
    },
    "percentiles4": {
        "total": 12704,
        "ok": 12704,
        "ko": 0
    },
    "group1": {
        "name": "t < 800 ms",
        "count": 3956,
        "percentage": 64
    },
    "group2": {
        "name": "800 ms < t < 1200 ms",
        "count": 749,
        "percentage": 12
    },
    "group3": {
        "name": "t > 1200 ms",
        "count": 1495,
        "percentage": 24
    },
    "group4": {
        "name": "failed",
        "count": 0,
        "percentage": 0
    },
    "meanNumberOfRequestsPerSecond": {
        "total": 35.02824858757062,
        "ok": 35.02824858757062,
        "ko": 0
    }
}
    },"req_autenticacao-1-51734": {
        "type": "REQUEST",
        "name": "Autenticacao_1",
"path": "Autenticacao_1",
"pathFormatted": "req_autenticacao-1-51734",
"stats": {
    "name": "Autenticacao_1",
    "numberOfRequests": {
        "total": 200,
        "ok": 0,
        "ko": 200
    },
    "minResponseTime": {
        "total": 42,
        "ok": 0,
        "ko": 42
    },
    "maxResponseTime": {
        "total": 2335,
        "ok": 0,
        "ko": 2335
    },
    "meanResponseTime": {
        "total": 343,
        "ok": 0,
        "ko": 343
    },
    "standardDeviation": {
        "total": 487,
        "ok": 0,
        "ko": 487
    },
    "percentiles1": {
        "total": 139,
        "ok": 0,
        "ko": 139
    },
    "percentiles2": {
        "total": 319,
        "ok": 0,
        "ko": 319
    },
    "percentiles3": {
        "total": 1370,
        "ok": 0,
        "ko": 1370
    },
    "percentiles4": {
        "total": 2290,
        "ok": 0,
        "ko": 2290
    },
    "group1": {
        "name": "t < 800 ms",
        "count": 0,
        "percentage": 0
    },
    "group2": {
        "name": "800 ms < t < 1200 ms",
        "count": 0,
        "percentage": 0
    },
    "group3": {
        "name": "t > 1200 ms",
        "count": 0,
        "percentage": 0
    },
    "group4": {
        "name": "failed",
        "count": 200,
        "percentage": 100
    },
    "meanNumberOfRequestsPerSecond": {
        "total": 1.1299435028248588,
        "ok": 0,
        "ko": 1.1299435028248588
    }
}
    },"req_request-33-6bb92": {
        "type": "REQUEST",
        "name": "request_33",
"path": "request_33",
"pathFormatted": "req_request-33-6bb92",
"stats": {
    "name": "request_33",
    "numberOfRequests": {
        "total": 200,
        "ok": 200,
        "ko": 0
    },
    "minResponseTime": {
        "total": 19,
        "ok": 19,
        "ko": 0
    },
    "maxResponseTime": {
        "total": 5870,
        "ok": 5870,
        "ko": 0
    },
    "meanResponseTime": {
        "total": 2007,
        "ok": 2007,
        "ko": 0
    },
    "standardDeviation": {
        "total": 2360,
        "ok": 2360,
        "ko": 0
    },
    "percentiles1": {
        "total": 539,
        "ok": 539,
        "ko": 0
    },
    "percentiles2": {
        "total": 5090,
        "ok": 5090,
        "ko": 0
    },
    "percentiles3": {
        "total": 5655,
        "ok": 5655,
        "ko": 0
    },
    "percentiles4": {
        "total": 5750,
        "ok": 5750,
        "ko": 0
    },
    "group1": {
        "name": "t < 800 ms",
        "count": 115,
        "percentage": 57
    },
    "group2": {
        "name": "800 ms < t < 1200 ms",
        "count": 15,
        "percentage": 8
    },
    "group3": {
        "name": "t > 1200 ms",
        "count": 70,
        "percentage": 35
    },
    "group4": {
        "name": "failed",
        "count": 0,
        "percentage": 0
    },
    "meanNumberOfRequestsPerSecond": {
        "total": 1.1299435028248588,
        "ok": 1.1299435028248588,
        "ko": 0
    }
}
    },"req_request-35-3745a": {
        "type": "REQUEST",
        "name": "request_35",
"path": "request_35",
"pathFormatted": "req_request-35-3745a",
"stats": {
    "name": "request_35",
    "numberOfRequests": {
        "total": 200,
        "ok": 200,
        "ko": 0
    },
    "minResponseTime": {
        "total": 21,
        "ok": 21,
        "ko": 0
    },
    "maxResponseTime": {
        "total": 7323,
        "ok": 7323,
        "ko": 0
    },
    "meanResponseTime": {
        "total": 1130,
        "ok": 1130,
        "ko": 0
    },
    "standardDeviation": {
        "total": 1773,
        "ok": 1773,
        "ko": 0
    },
    "percentiles1": {
        "total": 301,
        "ok": 301,
        "ko": 0
    },
    "percentiles2": {
        "total": 1235,
        "ok": 1235,
        "ko": 0
    },
    "percentiles3": {
        "total": 5438,
        "ok": 5438,
        "ko": 0
    },
    "percentiles4": {
        "total": 5737,
        "ok": 5737,
        "ko": 0
    },
    "group1": {
        "name": "t < 800 ms",
        "count": 134,
        "percentage": 67
    },
    "group2": {
        "name": "800 ms < t < 1200 ms",
        "count": 13,
        "percentage": 7
    },
    "group3": {
        "name": "t > 1200 ms",
        "count": 53,
        "percentage": 27
    },
    "group4": {
        "name": "failed",
        "count": 0,
        "percentage": 0
    },
    "meanNumberOfRequestsPerSecond": {
        "total": 1.1299435028248588,
        "ok": 1.1299435028248588,
        "ko": 0
    }
}
    },"req_req-listar-cate-b62a6": {
        "type": "REQUEST",
        "name": "req_listar_categoria_filho",
"path": "req_listar_categoria_filho",
"pathFormatted": "req_req-listar-cate-b62a6",
"stats": {
    "name": "req_listar_categoria_filho",
    "numberOfRequests": {
        "total": 600,
        "ok": 600,
        "ko": 0
    },
    "minResponseTime": {
        "total": 22,
        "ok": 22,
        "ko": 0
    },
    "maxResponseTime": {
        "total": 12461,
        "ok": 12461,
        "ko": 0
    },
    "meanResponseTime": {
        "total": 968,
        "ok": 968,
        "ko": 0
    },
    "standardDeviation": {
        "total": 1673,
        "ok": 1673,
        "ko": 0
    },
    "percentiles1": {
        "total": 362,
        "ok": 362,
        "ko": 0
    },
    "percentiles2": {
        "total": 721,
        "ok": 721,
        "ko": 0
    },
    "percentiles3": {
        "total": 5037,
        "ok": 5037,
        "ko": 0
    },
    "percentiles4": {
        "total": 8060,
        "ok": 8060,
        "ko": 0
    },
    "group1": {
        "name": "t < 800 ms",
        "count": 455,
        "percentage": 76
    },
    "group2": {
        "name": "800 ms < t < 1200 ms",
        "count": 35,
        "percentage": 6
    },
    "group3": {
        "name": "t > 1200 ms",
        "count": 110,
        "percentage": 18
    },
    "group4": {
        "name": "failed",
        "count": 0,
        "percentage": 0
    },
    "meanNumberOfRequestsPerSecond": {
        "total": 3.389830508474576,
        "ok": 3.389830508474576,
        "ko": 0
    }
}
    },"req_request-34-d9757": {
        "type": "REQUEST",
        "name": "request_34",
"path": "request_34",
"pathFormatted": "req_request-34-d9757",
"stats": {
    "name": "request_34",
    "numberOfRequests": {
        "total": 200,
        "ok": 200,
        "ko": 0
    },
    "minResponseTime": {
        "total": 20,
        "ok": 20,
        "ko": 0
    },
    "maxResponseTime": {
        "total": 5840,
        "ok": 5840,
        "ko": 0
    },
    "meanResponseTime": {
        "total": 1139,
        "ok": 1139,
        "ko": 0
    },
    "standardDeviation": {
        "total": 1749,
        "ok": 1749,
        "ko": 0
    },
    "percentiles1": {
        "total": 276,
        "ok": 276,
        "ko": 0
    },
    "percentiles2": {
        "total": 1166,
        "ok": 1166,
        "ko": 0
    },
    "percentiles3": {
        "total": 5372,
        "ok": 5372,
        "ko": 0
    },
    "percentiles4": {
        "total": 5726,
        "ok": 5726,
        "ko": 0
    },
    "group1": {
        "name": "t < 800 ms",
        "count": 138,
        "percentage": 69
    },
    "group2": {
        "name": "800 ms < t < 1200 ms",
        "count": 14,
        "percentage": 7
    },
    "group3": {
        "name": "t > 1200 ms",
        "count": 48,
        "percentage": 24
    },
    "group4": {
        "name": "failed",
        "count": 0,
        "percentage": 0
    },
    "meanNumberOfRequestsPerSecond": {
        "total": 1.1299435028248588,
        "ok": 1.1299435028248588,
        "ko": 0
    }
}
    },"req_req-listar-cate-d2a90": {
        "type": "REQUEST",
        "name": "req_listar_categoria_pai",
"path": "req_listar_categoria_pai",
"pathFormatted": "req_req-listar-cate-d2a90",
"stats": {
    "name": "req_listar_categoria_pai",
    "numberOfRequests": {
        "total": 600,
        "ok": 600,
        "ko": 0
    },
    "minResponseTime": {
        "total": 23,
        "ok": 23,
        "ko": 0
    },
    "maxResponseTime": {
        "total": 9830,
        "ok": 9830,
        "ko": 0
    },
    "meanResponseTime": {
        "total": 958,
        "ok": 958,
        "ko": 0
    },
    "standardDeviation": {
        "total": 1597,
        "ok": 1597,
        "ko": 0
    },
    "percentiles1": {
        "total": 372,
        "ok": 372,
        "ko": 0
    },
    "percentiles2": {
        "total": 721,
        "ok": 721,
        "ko": 0
    },
    "percentiles3": {
        "total": 4874,
        "ok": 4874,
        "ko": 0
    },
    "percentiles4": {
        "total": 7191,
        "ok": 7191,
        "ko": 0
    },
    "group1": {
        "name": "t < 800 ms",
        "count": 454,
        "percentage": 76
    },
    "group2": {
        "name": "800 ms < t < 1200 ms",
        "count": 37,
        "percentage": 6
    },
    "group3": {
        "name": "t > 1200 ms",
        "count": 109,
        "percentage": 18
    },
    "group4": {
        "name": "failed",
        "count": 0,
        "percentage": 0
    },
    "meanNumberOfRequestsPerSecond": {
        "total": 3.389830508474576,
        "ok": 3.389830508474576,
        "ko": 0
    }
}
    },"req_req-listar-cate-e0a0c": {
        "type": "REQUEST",
        "name": "req_listar_categoria_elasticsearch",
"path": "req_listar_categoria_elasticsearch",
"pathFormatted": "req_req-listar-cate-e0a0c",
"stats": {
    "name": "req_listar_categoria_elasticsearch",
    "numberOfRequests": {
        "total": 800,
        "ok": 800,
        "ko": 0
    },
    "minResponseTime": {
        "total": 21,
        "ok": 21,
        "ko": 0
    },
    "maxResponseTime": {
        "total": 41346,
        "ok": 41346,
        "ko": 0
    },
    "meanResponseTime": {
        "total": 1980,
        "ok": 1980,
        "ko": 0
    },
    "standardDeviation": {
        "total": 4129,
        "ok": 4129,
        "ko": 0
    },
    "percentiles1": {
        "total": 478,
        "ok": 478,
        "ko": 0
    },
    "percentiles2": {
        "total": 1201,
        "ok": 1201,
        "ko": 0
    },
    "percentiles3": {
        "total": 9010,
        "ok": 9010,
        "ko": 0
    },
    "percentiles4": {
        "total": 20979,
        "ok": 20979,
        "ko": 0
    },
    "group1": {
        "name": "t < 800 ms",
        "count": 533,
        "percentage": 67
    },
    "group2": {
        "name": "800 ms < t < 1200 ms",
        "count": 67,
        "percentage": 8
    },
    "group3": {
        "name": "t > 1200 ms",
        "count": 200,
        "percentage": 25
    },
    "group4": {
        "name": "failed",
        "count": 0,
        "percentage": 0
    },
    "meanNumberOfRequestsPerSecond": {
        "total": 4.519774011299435,
        "ok": 4.519774011299435,
        "ko": 0
    }
}
    },"req_request-45-1d986": {
        "type": "REQUEST",
        "name": "request_45",
"path": "request_45",
"pathFormatted": "req_request-45-1d986",
"stats": {
    "name": "request_45",
    "numberOfRequests": {
        "total": 200,
        "ok": 200,
        "ko": 0
    },
    "minResponseTime": {
        "total": 18,
        "ok": 18,
        "ko": 0
    },
    "maxResponseTime": {
        "total": 6796,
        "ok": 6796,
        "ko": 0
    },
    "meanResponseTime": {
        "total": 956,
        "ok": 956,
        "ko": 0
    },
    "standardDeviation": {
        "total": 1204,
        "ok": 1204,
        "ko": 0
    },
    "percentiles1": {
        "total": 564,
        "ok": 564,
        "ko": 0
    },
    "percentiles2": {
        "total": 1024,
        "ok": 1024,
        "ko": 0
    },
    "percentiles3": {
        "total": 3559,
        "ok": 3559,
        "ko": 0
    },
    "percentiles4": {
        "total": 5840,
        "ok": 5840,
        "ko": 0
    },
    "group1": {
        "name": "t < 800 ms",
        "count": 135,
        "percentage": 68
    },
    "group2": {
        "name": "800 ms < t < 1200 ms",
        "count": 27,
        "percentage": 14
    },
    "group3": {
        "name": "t > 1200 ms",
        "count": 38,
        "percentage": 19
    },
    "group4": {
        "name": "failed",
        "count": 0,
        "percentage": 0
    },
    "meanNumberOfRequestsPerSecond": {
        "total": 1.1299435028248588,
        "ok": 1.1299435028248588,
        "ko": 0
    }
}
    },"req_request-46-809be": {
        "type": "REQUEST",
        "name": "request_46",
"path": "request_46",
"pathFormatted": "req_request-46-809be",
"stats": {
    "name": "request_46",
    "numberOfRequests": {
        "total": 200,
        "ok": 200,
        "ko": 0
    },
    "minResponseTime": {
        "total": 20,
        "ok": 20,
        "ko": 0
    },
    "maxResponseTime": {
        "total": 6291,
        "ok": 6291,
        "ko": 0
    },
    "meanResponseTime": {
        "total": 734,
        "ok": 734,
        "ko": 0
    },
    "standardDeviation": {
        "total": 1007,
        "ok": 1007,
        "ko": 0
    },
    "percentiles1": {
        "total": 468,
        "ok": 468,
        "ko": 0
    },
    "percentiles2": {
        "total": 915,
        "ok": 915,
        "ko": 0
    },
    "percentiles3": {
        "total": 2374,
        "ok": 2374,
        "ko": 0
    },
    "percentiles4": {
        "total": 5471,
        "ok": 5471,
        "ko": 0
    },
    "group1": {
        "name": "t < 800 ms",
        "count": 141,
        "percentage": 71
    },
    "group2": {
        "name": "800 ms < t < 1200 ms",
        "count": 32,
        "percentage": 16
    },
    "group3": {
        "name": "t > 1200 ms",
        "count": 27,
        "percentage": 14
    },
    "group4": {
        "name": "failed",
        "count": 0,
        "percentage": 0
    },
    "meanNumberOfRequestsPerSecond": {
        "total": 1.1299435028248588,
        "ok": 1.1299435028248588,
        "ko": 0
    }
}
    },"req_request-47-f8703": {
        "type": "REQUEST",
        "name": "request_47",
"path": "request_47",
"pathFormatted": "req_request-47-f8703",
"stats": {
    "name": "request_47",
    "numberOfRequests": {
        "total": 200,
        "ok": 200,
        "ko": 0
    },
    "minResponseTime": {
        "total": 21,
        "ok": 21,
        "ko": 0
    },
    "maxResponseTime": {
        "total": 7551,
        "ok": 7551,
        "ko": 0
    },
    "meanResponseTime": {
        "total": 835,
        "ok": 835,
        "ko": 0
    },
    "standardDeviation": {
        "total": 1249,
        "ok": 1249,
        "ko": 0
    },
    "percentiles1": {
        "total": 468,
        "ok": 468,
        "ko": 0
    },
    "percentiles2": {
        "total": 939,
        "ok": 939,
        "ko": 0
    },
    "percentiles3": {
        "total": 3310,
        "ok": 3310,
        "ko": 0
    },
    "percentiles4": {
        "total": 5883,
        "ok": 5883,
        "ko": 0
    },
    "group1": {
        "name": "t < 800 ms",
        "count": 141,
        "percentage": 71
    },
    "group2": {
        "name": "800 ms < t < 1200 ms",
        "count": 27,
        "percentage": 14
    },
    "group3": {
        "name": "t > 1200 ms",
        "count": 32,
        "percentage": 16
    },
    "group4": {
        "name": "failed",
        "count": 0,
        "percentage": 0
    },
    "meanNumberOfRequestsPerSecond": {
        "total": 1.1299435028248588,
        "ok": 1.1299435028248588,
        "ko": 0
    }
}
    },"req_request-52-eab3a": {
        "type": "REQUEST",
        "name": "request_52",
"path": "request_52",
"pathFormatted": "req_request-52-eab3a",
"stats": {
    "name": "request_52",
    "numberOfRequests": {
        "total": 200,
        "ok": 200,
        "ko": 0
    },
    "minResponseTime": {
        "total": 19,
        "ok": 19,
        "ko": 0
    },
    "maxResponseTime": {
        "total": 12099,
        "ok": 12099,
        "ko": 0
    },
    "meanResponseTime": {
        "total": 771,
        "ok": 771,
        "ko": 0
    },
    "standardDeviation": {
        "total": 1171,
        "ok": 1171,
        "ko": 0
    },
    "percentiles1": {
        "total": 457,
        "ok": 457,
        "ko": 0
    },
    "percentiles2": {
        "total": 828,
        "ok": 828,
        "ko": 0
    },
    "percentiles3": {
        "total": 2420,
        "ok": 2420,
        "ko": 0
    },
    "percentiles4": {
        "total": 5664,
        "ok": 5664,
        "ko": 0
    },
    "group1": {
        "name": "t < 800 ms",
        "count": 149,
        "percentage": 75
    },
    "group2": {
        "name": "800 ms < t < 1200 ms",
        "count": 26,
        "percentage": 13
    },
    "group3": {
        "name": "t > 1200 ms",
        "count": 25,
        "percentage": 13
    },
    "group4": {
        "name": "failed",
        "count": 0,
        "percentage": 0
    },
    "meanNumberOfRequestsPerSecond": {
        "total": 1.1299435028248588,
        "ok": 1.1299435028248588,
        "ko": 0
    }
}
    },"req_req-quantidade--69317": {
        "type": "REQUEST",
        "name": "req_quantidade_favorito",
"path": "req_quantidade_favorito",
"pathFormatted": "req_req-quantidade--69317",
"stats": {
    "name": "req_quantidade_favorito",
    "numberOfRequests": {
        "total": 2200,
        "ok": 2200,
        "ko": 0
    },
    "minResponseTime": {
        "total": 24,
        "ok": 24,
        "ko": 0
    },
    "maxResponseTime": {
        "total": 12931,
        "ok": 12931,
        "ko": 0
    },
    "meanResponseTime": {
        "total": 1113,
        "ok": 1113,
        "ko": 0
    },
    "standardDeviation": {
        "total": 1675,
        "ok": 1675,
        "ko": 0
    },
    "percentiles1": {
        "total": 517,
        "ok": 517,
        "ko": 0
    },
    "percentiles2": {
        "total": 1185,
        "ok": 1185,
        "ko": 0
    },
    "percentiles3": {
        "total": 4749,
        "ok": 4749,
        "ko": 0
    },
    "percentiles4": {
        "total": 8692,
        "ok": 8692,
        "ko": 0
    },
    "group1": {
        "name": "t < 800 ms",
        "count": 1395,
        "percentage": 63
    },
    "group2": {
        "name": "800 ms < t < 1200 ms",
        "count": 266,
        "percentage": 12
    },
    "group3": {
        "name": "t > 1200 ms",
        "count": 539,
        "percentage": 25
    },
    "group4": {
        "name": "failed",
        "count": 0,
        "percentage": 0
    },
    "meanNumberOfRequestsPerSecond": {
        "total": 12.429378531073446,
        "ok": 12.429378531073446,
        "ko": 0
    }
}
    },"req_request-54-22e8b": {
        "type": "REQUEST",
        "name": "request_54",
"path": "request_54",
"pathFormatted": "req_request-54-22e8b",
"stats": {
    "name": "request_54",
    "numberOfRequests": {
        "total": 200,
        "ok": 200,
        "ko": 0
    },
    "minResponseTime": {
        "total": 29,
        "ok": 29,
        "ko": 0
    },
    "maxResponseTime": {
        "total": 11174,
        "ok": 11174,
        "ko": 0
    },
    "meanResponseTime": {
        "total": 880,
        "ok": 880,
        "ko": 0
    },
    "standardDeviation": {
        "total": 1271,
        "ok": 1271,
        "ko": 0
    },
    "percentiles1": {
        "total": 482,
        "ok": 482,
        "ko": 0
    },
    "percentiles2": {
        "total": 893,
        "ok": 893,
        "ko": 0
    },
    "percentiles3": {
        "total": 4127,
        "ok": 4127,
        "ko": 0
    },
    "percentiles4": {
        "total": 5055,
        "ok": 5055,
        "ko": 0
    },
    "group1": {
        "name": "t < 800 ms",
        "count": 146,
        "percentage": 73
    },
    "group2": {
        "name": "800 ms < t < 1200 ms",
        "count": 20,
        "percentage": 10
    },
    "group3": {
        "name": "t > 1200 ms",
        "count": 34,
        "percentage": 17
    },
    "group4": {
        "name": "failed",
        "count": 0,
        "percentage": 0
    },
    "meanNumberOfRequestsPerSecond": {
        "total": 1.1299435028248588,
        "ok": 1.1299435028248588,
        "ko": 0
    }
}
    },"req_request-53-369eb": {
        "type": "REQUEST",
        "name": "request_53",
"path": "request_53",
"pathFormatted": "req_request-53-369eb",
"stats": {
    "name": "request_53",
    "numberOfRequests": {
        "total": 200,
        "ok": 200,
        "ko": 0
    },
    "minResponseTime": {
        "total": 29,
        "ok": 29,
        "ko": 0
    },
    "maxResponseTime": {
        "total": 5201,
        "ok": 5201,
        "ko": 0
    },
    "meanResponseTime": {
        "total": 841,
        "ok": 841,
        "ko": 0
    },
    "standardDeviation": {
        "total": 1061,
        "ok": 1061,
        "ko": 0
    },
    "percentiles1": {
        "total": 482,
        "ok": 482,
        "ko": 0
    },
    "percentiles2": {
        "total": 891,
        "ok": 891,
        "ko": 0
    },
    "percentiles3": {
        "total": 4103,
        "ok": 4103,
        "ko": 0
    },
    "percentiles4": {
        "total": 5030,
        "ok": 5030,
        "ko": 0
    },
    "group1": {
        "name": "t < 800 ms",
        "count": 144,
        "percentage": 72
    },
    "group2": {
        "name": "800 ms < t < 1200 ms",
        "count": 24,
        "percentage": 12
    },
    "group3": {
        "name": "t > 1200 ms",
        "count": 32,
        "percentage": 16
    },
    "group4": {
        "name": "failed",
        "count": 0,
        "percentage": 0
    },
    "meanNumberOfRequestsPerSecond": {
        "total": 1.1299435028248588,
        "ok": 1.1299435028248588,
        "ko": 0
    }
}
    },"req_request-94-27500": {
        "type": "REQUEST",
        "name": "request_94",
"path": "request_94",
"pathFormatted": "req_request-94-27500",
"stats": {
    "name": "request_94",
    "numberOfRequests": {
        "total": 200,
        "ok": 200,
        "ko": 0
    },
    "minResponseTime": {
        "total": 20,
        "ok": 20,
        "ko": 0
    },
    "maxResponseTime": {
        "total": 6257,
        "ok": 6257,
        "ko": 0
    },
    "meanResponseTime": {
        "total": 840,
        "ok": 840,
        "ko": 0
    },
    "standardDeviation": {
        "total": 1112,
        "ok": 1112,
        "ko": 0
    },
    "percentiles1": {
        "total": 455,
        "ok": 455,
        "ko": 0
    },
    "percentiles2": {
        "total": 822,
        "ok": 822,
        "ko": 0
    },
    "percentiles3": {
        "total": 3394,
        "ok": 3394,
        "ko": 0
    },
    "percentiles4": {
        "total": 5242,
        "ok": 5242,
        "ko": 0
    },
    "group1": {
        "name": "t < 800 ms",
        "count": 146,
        "percentage": 73
    },
    "group2": {
        "name": "800 ms < t < 1200 ms",
        "count": 27,
        "percentage": 14
    },
    "group3": {
        "name": "t > 1200 ms",
        "count": 27,
        "percentage": 14
    },
    "group4": {
        "name": "failed",
        "count": 0,
        "percentage": 0
    },
    "meanNumberOfRequestsPerSecond": {
        "total": 1.1299435028248588,
        "ok": 1.1299435028248588,
        "ko": 0
    }
}
    },"req_request-96-b8b8c": {
        "type": "REQUEST",
        "name": "request_96",
"path": "request_96",
"pathFormatted": "req_request-96-b8b8c",
"stats": {
    "name": "request_96",
    "numberOfRequests": {
        "total": 200,
        "ok": 200,
        "ko": 0
    },
    "minResponseTime": {
        "total": 25,
        "ok": 25,
        "ko": 0
    },
    "maxResponseTime": {
        "total": 5231,
        "ok": 5231,
        "ko": 0
    },
    "meanResponseTime": {
        "total": 705,
        "ok": 705,
        "ko": 0
    },
    "standardDeviation": {
        "total": 912,
        "ok": 912,
        "ko": 0
    },
    "percentiles1": {
        "total": 440,
        "ok": 440,
        "ko": 0
    },
    "percentiles2": {
        "total": 801,
        "ok": 801,
        "ko": 0
    },
    "percentiles3": {
        "total": 2313,
        "ok": 2313,
        "ko": 0
    },
    "percentiles4": {
        "total": 4731,
        "ok": 4731,
        "ko": 0
    },
    "group1": {
        "name": "t < 800 ms",
        "count": 150,
        "percentage": 75
    },
    "group2": {
        "name": "800 ms < t < 1200 ms",
        "count": 29,
        "percentage": 14
    },
    "group3": {
        "name": "t > 1200 ms",
        "count": 21,
        "percentage": 11
    },
    "group4": {
        "name": "failed",
        "count": 0,
        "percentage": 0
    },
    "meanNumberOfRequestsPerSecond": {
        "total": 1.1299435028248588,
        "ok": 1.1299435028248588,
        "ko": 0
    }
}
    },"req_req-get-empresa-9f139": {
        "type": "REQUEST",
        "name": "req_get_empresa",
"path": "req_get_empresa",
"pathFormatted": "req_req-get-empresa-9f139",
"stats": {
    "name": "req_get_empresa",
    "numberOfRequests": {
        "total": 600,
        "ok": 600,
        "ko": 0
    },
    "minResponseTime": {
        "total": 23,
        "ok": 23,
        "ko": 0
    },
    "maxResponseTime": {
        "total": 7095,
        "ok": 7095,
        "ko": 0
    },
    "meanResponseTime": {
        "total": 558,
        "ok": 558,
        "ko": 0
    },
    "standardDeviation": {
        "total": 794,
        "ok": 794,
        "ko": 0
    },
    "percentiles1": {
        "total": 347,
        "ok": 347,
        "ko": 0
    },
    "percentiles2": {
        "total": 634,
        "ok": 634,
        "ko": 0
    },
    "percentiles3": {
        "total": 1459,
        "ok": 1459,
        "ko": 0
    },
    "percentiles4": {
        "total": 4728,
        "ok": 4728,
        "ko": 0
    },
    "group1": {
        "name": "t < 800 ms",
        "count": 505,
        "percentage": 84
    },
    "group2": {
        "name": "800 ms < t < 1200 ms",
        "count": 51,
        "percentage": 9
    },
    "group3": {
        "name": "t > 1200 ms",
        "count": 44,
        "percentage": 7
    },
    "group4": {
        "name": "failed",
        "count": 0,
        "percentage": 0
    },
    "meanNumberOfRequestsPerSecond": {
        "total": 3.389830508474576,
        "ok": 3.389830508474576,
        "ko": 0
    }
}
    },"req_req-qntd-anunci-44e28": {
        "type": "REQUEST",
        "name": "req_qntd_anuncio",
"path": "req_qntd_anuncio",
"pathFormatted": "req_req-qntd-anunci-44e28",
"stats": {
    "name": "req_qntd_anuncio",
    "numberOfRequests": {
        "total": 600,
        "ok": 600,
        "ko": 0
    },
    "minResponseTime": {
        "total": 23,
        "ok": 23,
        "ko": 0
    },
    "maxResponseTime": {
        "total": 18413,
        "ok": 18413,
        "ko": 0
    },
    "meanResponseTime": {
        "total": 615,
        "ok": 615,
        "ko": 0
    },
    "standardDeviation": {
        "total": 1193,
        "ok": 1193,
        "ko": 0
    },
    "percentiles1": {
        "total": 344,
        "ok": 344,
        "ko": 0
    },
    "percentiles2": {
        "total": 629,
        "ok": 629,
        "ko": 0
    },
    "percentiles3": {
        "total": 1552,
        "ok": 1552,
        "ko": 0
    },
    "percentiles4": {
        "total": 4999,
        "ok": 4999,
        "ko": 0
    },
    "group1": {
        "name": "t < 800 ms",
        "count": 499,
        "percentage": 83
    },
    "group2": {
        "name": "800 ms < t < 1200 ms",
        "count": 53,
        "percentage": 9
    },
    "group3": {
        "name": "t > 1200 ms",
        "count": 48,
        "percentage": 8
    },
    "group4": {
        "name": "failed",
        "count": 0,
        "percentage": 0
    },
    "meanNumberOfRequestsPerSecond": {
        "total": 3.389830508474576,
        "ok": 3.389830508474576,
        "ko": 0
    }
}
    },"req_req-detalhar-an-2b1d2": {
        "type": "REQUEST",
        "name": "req_detalhar_anuncio",
"path": "req_detalhar_anuncio",
"pathFormatted": "req_req-detalhar-an-2b1d2",
"stats": {
    "name": "req_detalhar_anuncio",
    "numberOfRequests": {
        "total": 600,
        "ok": 600,
        "ko": 0
    },
    "minResponseTime": {
        "total": 20,
        "ok": 20,
        "ko": 0
    },
    "maxResponseTime": {
        "total": 7747,
        "ok": 7747,
        "ko": 0
    },
    "meanResponseTime": {
        "total": 548,
        "ok": 548,
        "ko": 0
    },
    "standardDeviation": {
        "total": 815,
        "ok": 815,
        "ko": 0
    },
    "percentiles1": {
        "total": 333,
        "ok": 333,
        "ko": 0
    },
    "percentiles2": {
        "total": 615,
        "ok": 615,
        "ko": 0
    },
    "percentiles3": {
        "total": 1433,
        "ok": 1433,
        "ko": 0
    },
    "percentiles4": {
        "total": 5000,
        "ok": 5000,
        "ko": 0
    },
    "group1": {
        "name": "t < 800 ms",
        "count": 508,
        "percentage": 85
    },
    "group2": {
        "name": "800 ms < t < 1200 ms",
        "count": 51,
        "percentage": 9
    },
    "group3": {
        "name": "t > 1200 ms",
        "count": 41,
        "percentage": 7
    },
    "group4": {
        "name": "failed",
        "count": 0,
        "percentage": 0
    },
    "meanNumberOfRequestsPerSecond": {
        "total": 3.389830508474576,
        "ok": 3.389830508474576,
        "ko": 0
    }
}
    },"req_request-95-02d41": {
        "type": "REQUEST",
        "name": "request_95",
"path": "request_95",
"pathFormatted": "req_request-95-02d41",
"stats": {
    "name": "request_95",
    "numberOfRequests": {
        "total": 200,
        "ok": 200,
        "ko": 0
    },
    "minResponseTime": {
        "total": 23,
        "ok": 23,
        "ko": 0
    },
    "maxResponseTime": {
        "total": 5231,
        "ok": 5231,
        "ko": 0
    },
    "meanResponseTime": {
        "total": 692,
        "ok": 692,
        "ko": 0
    },
    "standardDeviation": {
        "total": 893,
        "ok": 893,
        "ko": 0
    },
    "percentiles1": {
        "total": 443,
        "ok": 443,
        "ko": 0
    },
    "percentiles2": {
        "total": 796,
        "ok": 796,
        "ko": 0
    },
    "percentiles3": {
        "total": 1699,
        "ok": 1699,
        "ko": 0
    },
    "percentiles4": {
        "total": 4731,
        "ok": 4731,
        "ko": 0
    },
    "group1": {
        "name": "t < 800 ms",
        "count": 150,
        "percentage": 75
    },
    "group2": {
        "name": "800 ms < t < 1200 ms",
        "count": 31,
        "percentage": 16
    },
    "group3": {
        "name": "t > 1200 ms",
        "count": 19,
        "percentage": 10
    },
    "group4": {
        "name": "failed",
        "count": 0,
        "percentage": 0
    },
    "meanNumberOfRequestsPerSecond": {
        "total": 1.1299435028248588,
        "ok": 1.1299435028248588,
        "ko": 0
    }
}
    },"req_req-favoritado-c9094": {
        "type": "REQUEST",
        "name": "req_favoritado",
"path": "req_favoritado",
"pathFormatted": "req_req-favoritado-c9094",
"stats": {
    "name": "req_favoritado",
    "numberOfRequests": {
        "total": 600,
        "ok": 600,
        "ko": 0
    },
    "minResponseTime": {
        "total": 19,
        "ok": 19,
        "ko": 0
    },
    "maxResponseTime": {
        "total": 7747,
        "ok": 7747,
        "ko": 0
    },
    "meanResponseTime": {
        "total": 548,
        "ok": 548,
        "ko": 0
    },
    "standardDeviation": {
        "total": 822,
        "ok": 822,
        "ko": 0
    },
    "percentiles1": {
        "total": 335,
        "ok": 335,
        "ko": 0
    },
    "percentiles2": {
        "total": 613,
        "ok": 613,
        "ko": 0
    },
    "percentiles3": {
        "total": 1380,
        "ok": 1380,
        "ko": 0
    },
    "percentiles4": {
        "total": 4999,
        "ok": 4999,
        "ko": 0
    },
    "group1": {
        "name": "t < 800 ms",
        "count": 505,
        "percentage": 84
    },
    "group2": {
        "name": "800 ms < t < 1200 ms",
        "count": 55,
        "percentage": 9
    },
    "group3": {
        "name": "t > 1200 ms",
        "count": 40,
        "percentage": 7
    },
    "group4": {
        "name": "failed",
        "count": 0,
        "percentage": 0
    },
    "meanNumberOfRequestsPerSecond": {
        "total": 3.389830508474576,
        "ok": 3.389830508474576,
        "ko": 0
    }
}
    },"req_req-nota-anunci-c34a8": {
        "type": "REQUEST",
        "name": "req_nota_anuncio",
"path": "req_nota_anuncio",
"pathFormatted": "req_req-nota-anunci-c34a8",
"stats": {
    "name": "req_nota_anuncio",
    "numberOfRequests": {
        "total": 600,
        "ok": 600,
        "ko": 0
    },
    "minResponseTime": {
        "total": 24,
        "ok": 24,
        "ko": 0
    },
    "maxResponseTime": {
        "total": 10029,
        "ok": 10029,
        "ko": 0
    },
    "meanResponseTime": {
        "total": 579,
        "ok": 579,
        "ko": 0
    },
    "standardDeviation": {
        "total": 911,
        "ok": 911,
        "ko": 0
    },
    "percentiles1": {
        "total": 342,
        "ok": 342,
        "ko": 0
    },
    "percentiles2": {
        "total": 616,
        "ok": 616,
        "ko": 0
    },
    "percentiles3": {
        "total": 1476,
        "ok": 1476,
        "ko": 0
    },
    "percentiles4": {
        "total": 4999,
        "ok": 4999,
        "ko": 0
    },
    "group1": {
        "name": "t < 800 ms",
        "count": 502,
        "percentage": 84
    },
    "group2": {
        "name": "800 ms < t < 1200 ms",
        "count": 55,
        "percentage": 9
    },
    "group3": {
        "name": "t > 1200 ms",
        "count": 43,
        "percentage": 7
    },
    "group4": {
        "name": "failed",
        "count": 0,
        "percentage": 0
    },
    "meanNumberOfRequestsPerSecond": {
        "total": 3.389830508474576,
        "ok": 3.389830508474576,
        "ko": 0
    }
}
    },"req_req-avaliacao-a-cf651": {
        "type": "REQUEST",
        "name": "req_avaliacao_anuncio",
"path": "req_avaliacao_anuncio",
"pathFormatted": "req_req-avaliacao-a-cf651",
"stats": {
    "name": "req_avaliacao_anuncio",
    "numberOfRequests": {
        "total": 600,
        "ok": 600,
        "ko": 0
    },
    "minResponseTime": {
        "total": 21,
        "ok": 21,
        "ko": 0
    },
    "maxResponseTime": {
        "total": 6795,
        "ok": 6795,
        "ko": 0
    },
    "meanResponseTime": {
        "total": 536,
        "ok": 536,
        "ko": 0
    },
    "standardDeviation": {
        "total": 827,
        "ok": 827,
        "ko": 0
    },
    "percentiles1": {
        "total": 309,
        "ok": 309,
        "ko": 0
    },
    "percentiles2": {
        "total": 558,
        "ok": 558,
        "ko": 0
    },
    "percentiles3": {
        "total": 1649,
        "ok": 1649,
        "ko": 0
    },
    "percentiles4": {
        "total": 4828,
        "ok": 4828,
        "ko": 0
    },
    "group1": {
        "name": "t < 800 ms",
        "count": 509,
        "percentage": 85
    },
    "group2": {
        "name": "800 ms < t < 1200 ms",
        "count": 40,
        "percentage": 7
    },
    "group3": {
        "name": "t > 1200 ms",
        "count": 51,
        "percentage": 9
    },
    "group4": {
        "name": "failed",
        "count": 0,
        "percentage": 0
    },
    "meanNumberOfRequestsPerSecond": {
        "total": 3.389830508474576,
        "ok": 3.389830508474576,
        "ko": 0
    }
}
    },"req_request-117-295ce": {
        "type": "REQUEST",
        "name": "request_117",
"path": "request_117",
"pathFormatted": "req_request-117-295ce",
"stats": {
    "name": "request_117",
    "numberOfRequests": {
        "total": 200,
        "ok": 200,
        "ko": 0
    },
    "minResponseTime": {
        "total": 20,
        "ok": 20,
        "ko": 0
    },
    "maxResponseTime": {
        "total": 6089,
        "ok": 6089,
        "ko": 0
    },
    "meanResponseTime": {
        "total": 745,
        "ok": 745,
        "ko": 0
    },
    "standardDeviation": {
        "total": 967,
        "ok": 967,
        "ko": 0
    },
    "percentiles1": {
        "total": 475,
        "ok": 475,
        "ko": 0
    },
    "percentiles2": {
        "total": 838,
        "ok": 838,
        "ko": 0
    },
    "percentiles3": {
        "total": 2208,
        "ok": 2208,
        "ko": 0
    },
    "percentiles4": {
        "total": 4897,
        "ok": 4897,
        "ko": 0
    },
    "group1": {
        "name": "t < 800 ms",
        "count": 143,
        "percentage": 72
    },
    "group2": {
        "name": "800 ms < t < 1200 ms",
        "count": 32,
        "percentage": 16
    },
    "group3": {
        "name": "t > 1200 ms",
        "count": 25,
        "percentage": 13
    },
    "group4": {
        "name": "failed",
        "count": 0,
        "percentage": 0
    },
    "meanNumberOfRequestsPerSecond": {
        "total": 1.1299435028248588,
        "ok": 1.1299435028248588,
        "ko": 0
    }
}
    },"req_request-119-a6957": {
        "type": "REQUEST",
        "name": "request_119",
"path": "request_119",
"pathFormatted": "req_request-119-a6957",
"stats": {
    "name": "request_119",
    "numberOfRequests": {
        "total": 200,
        "ok": 200,
        "ko": 0
    },
    "minResponseTime": {
        "total": 22,
        "ok": 22,
        "ko": 0
    },
    "maxResponseTime": {
        "total": 5904,
        "ok": 5904,
        "ko": 0
    },
    "meanResponseTime": {
        "total": 606,
        "ok": 606,
        "ko": 0
    },
    "standardDeviation": {
        "total": 842,
        "ok": 842,
        "ko": 0
    },
    "percentiles1": {
        "total": 376,
        "ok": 376,
        "ko": 0
    },
    "percentiles2": {
        "total": 669,
        "ok": 669,
        "ko": 0
    },
    "percentiles3": {
        "total": 1603,
        "ok": 1603,
        "ko": 0
    },
    "percentiles4": {
        "total": 5758,
        "ok": 5758,
        "ko": 0
    },
    "group1": {
        "name": "t < 800 ms",
        "count": 158,
        "percentage": 79
    },
    "group2": {
        "name": "800 ms < t < 1200 ms",
        "count": 18,
        "percentage": 9
    },
    "group3": {
        "name": "t > 1200 ms",
        "count": 24,
        "percentage": 12
    },
    "group4": {
        "name": "failed",
        "count": 0,
        "percentage": 0
    },
    "meanNumberOfRequestsPerSecond": {
        "total": 1.1299435028248588,
        "ok": 1.1299435028248588,
        "ko": 0
    }
}
    },"req_request-118-dd81f": {
        "type": "REQUEST",
        "name": "request_118",
"path": "request_118",
"pathFormatted": "req_request-118-dd81f",
"stats": {
    "name": "request_118",
    "numberOfRequests": {
        "total": 200,
        "ok": 200,
        "ko": 0
    },
    "minResponseTime": {
        "total": 21,
        "ok": 21,
        "ko": 0
    },
    "maxResponseTime": {
        "total": 5758,
        "ok": 5758,
        "ko": 0
    },
    "meanResponseTime": {
        "total": 550,
        "ok": 550,
        "ko": 0
    },
    "standardDeviation": {
        "total": 659,
        "ok": 659,
        "ko": 0
    },
    "percentiles1": {
        "total": 376,
        "ok": 376,
        "ko": 0
    },
    "percentiles2": {
        "total": 653,
        "ok": 653,
        "ko": 0
    },
    "percentiles3": {
        "total": 1442,
        "ok": 1442,
        "ko": 0
    },
    "percentiles4": {
        "total": 3560,
        "ok": 3560,
        "ko": 0
    },
    "group1": {
        "name": "t < 800 ms",
        "count": 160,
        "percentage": 80
    },
    "group2": {
        "name": "800 ms < t < 1200 ms",
        "count": 18,
        "percentage": 9
    },
    "group3": {
        "name": "t > 1200 ms",
        "count": 22,
        "percentage": 11
    },
    "group4": {
        "name": "failed",
        "count": 0,
        "percentage": 0
    },
    "meanNumberOfRequestsPerSecond": {
        "total": 1.1299435028248588,
        "ok": 1.1299435028248588,
        "ko": 0
    }
}
    },"req_request-124-6f41c": {
        "type": "REQUEST",
        "name": "request_124",
"path": "request_124",
"pathFormatted": "req_request-124-6f41c",
"stats": {
    "name": "request_124",
    "numberOfRequests": {
        "total": 200,
        "ok": 200,
        "ko": 0
    },
    "minResponseTime": {
        "total": 20,
        "ok": 20,
        "ko": 0
    },
    "maxResponseTime": {
        "total": 5414,
        "ok": 5414,
        "ko": 0
    },
    "meanResponseTime": {
        "total": 561,
        "ok": 561,
        "ko": 0
    },
    "standardDeviation": {
        "total": 527,
        "ok": 527,
        "ko": 0
    },
    "percentiles1": {
        "total": 463,
        "ok": 463,
        "ko": 0
    },
    "percentiles2": {
        "total": 675,
        "ok": 675,
        "ko": 0
    },
    "percentiles3": {
        "total": 1288,
        "ok": 1288,
        "ko": 0
    },
    "percentiles4": {
        "total": 2313,
        "ok": 2313,
        "ko": 0
    },
    "group1": {
        "name": "t < 800 ms",
        "count": 163,
        "percentage": 82
    },
    "group2": {
        "name": "800 ms < t < 1200 ms",
        "count": 23,
        "percentage": 12
    },
    "group3": {
        "name": "t > 1200 ms",
        "count": 14,
        "percentage": 7
    },
    "group4": {
        "name": "failed",
        "count": 0,
        "percentage": 0
    },
    "meanNumberOfRequestsPerSecond": {
        "total": 1.1299435028248588,
        "ok": 1.1299435028248588,
        "ko": 0
    }
}
    },"req_request-125-b3349": {
        "type": "REQUEST",
        "name": "request_125",
"path": "request_125",
"pathFormatted": "req_request-125-b3349",
"stats": {
    "name": "request_125",
    "numberOfRequests": {
        "total": 200,
        "ok": 200,
        "ko": 0
    },
    "minResponseTime": {
        "total": 20,
        "ok": 20,
        "ko": 0
    },
    "maxResponseTime": {
        "total": 6534,
        "ok": 6534,
        "ko": 0
    },
    "meanResponseTime": {
        "total": 542,
        "ok": 542,
        "ko": 0
    },
    "standardDeviation": {
        "total": 761,
        "ok": 761,
        "ko": 0
    },
    "percentiles1": {
        "total": 373,
        "ok": 373,
        "ko": 0
    },
    "percentiles2": {
        "total": 626,
        "ok": 626,
        "ko": 0
    },
    "percentiles3": {
        "total": 1266,
        "ok": 1266,
        "ko": 0
    },
    "percentiles4": {
        "total": 4642,
        "ok": 4642,
        "ko": 0
    },
    "group1": {
        "name": "t < 800 ms",
        "count": 168,
        "percentage": 84
    },
    "group2": {
        "name": "800 ms < t < 1200 ms",
        "count": 17,
        "percentage": 9
    },
    "group3": {
        "name": "t > 1200 ms",
        "count": 15,
        "percentage": 8
    },
    "group4": {
        "name": "failed",
        "count": 0,
        "percentage": 0
    },
    "meanNumberOfRequestsPerSecond": {
        "total": 1.1299435028248588,
        "ok": 1.1299435028248588,
        "ko": 0
    }
}
    },"req_request-126-4efb6": {
        "type": "REQUEST",
        "name": "request_126",
"path": "request_126",
"pathFormatted": "req_request-126-4efb6",
"stats": {
    "name": "request_126",
    "numberOfRequests": {
        "total": 200,
        "ok": 200,
        "ko": 0
    },
    "minResponseTime": {
        "total": 21,
        "ok": 21,
        "ko": 0
    },
    "maxResponseTime": {
        "total": 7264,
        "ok": 7264,
        "ko": 0
    },
    "meanResponseTime": {
        "total": 546,
        "ok": 546,
        "ko": 0
    },
    "standardDeviation": {
        "total": 800,
        "ok": 800,
        "ko": 0
    },
    "percentiles1": {
        "total": 375,
        "ok": 375,
        "ko": 0
    },
    "percentiles2": {
        "total": 626,
        "ok": 626,
        "ko": 0
    },
    "percentiles3": {
        "total": 1232,
        "ok": 1232,
        "ko": 0
    },
    "percentiles4": {
        "total": 4651,
        "ok": 4651,
        "ko": 0
    },
    "group1": {
        "name": "t < 800 ms",
        "count": 167,
        "percentage": 84
    },
    "group2": {
        "name": "800 ms < t < 1200 ms",
        "count": 20,
        "percentage": 10
    },
    "group3": {
        "name": "t > 1200 ms",
        "count": 13,
        "percentage": 7
    },
    "group4": {
        "name": "failed",
        "count": 0,
        "percentage": 0
    },
    "meanNumberOfRequestsPerSecond": {
        "total": 1.1299435028248588,
        "ok": 1.1299435028248588,
        "ko": 0
    }
}
    },"req_request-130-ff42a": {
        "type": "REQUEST",
        "name": "request_130",
"path": "request_130",
"pathFormatted": "req_request-130-ff42a",
"stats": {
    "name": "request_130",
    "numberOfRequests": {
        "total": 200,
        "ok": 200,
        "ko": 0
    },
    "minResponseTime": {
        "total": 19,
        "ok": 19,
        "ko": 0
    },
    "maxResponseTime": {
        "total": 6066,
        "ok": 6066,
        "ko": 0
    },
    "meanResponseTime": {
        "total": 636,
        "ok": 636,
        "ko": 0
    },
    "standardDeviation": {
        "total": 662,
        "ok": 662,
        "ko": 0
    },
    "percentiles1": {
        "total": 483,
        "ok": 483,
        "ko": 0
    },
    "percentiles2": {
        "total": 787,
        "ok": 787,
        "ko": 0
    },
    "percentiles3": {
        "total": 1534,
        "ok": 1534,
        "ko": 0
    },
    "percentiles4": {
        "total": 2900,
        "ok": 2900,
        "ko": 0
    },
    "group1": {
        "name": "t < 800 ms",
        "count": 152,
        "percentage": 76
    },
    "group2": {
        "name": "800 ms < t < 1200 ms",
        "count": 29,
        "percentage": 14
    },
    "group3": {
        "name": "t > 1200 ms",
        "count": 19,
        "percentage": 10
    },
    "group4": {
        "name": "failed",
        "count": 0,
        "percentage": 0
    },
    "meanNumberOfRequestsPerSecond": {
        "total": 1.1299435028248588,
        "ok": 1.1299435028248588,
        "ko": 0
    }
}
    },"req_request-131-22210": {
        "type": "REQUEST",
        "name": "request_131",
"path": "request_131",
"pathFormatted": "req_request-131-22210",
"stats": {
    "name": "request_131",
    "numberOfRequests": {
        "total": 200,
        "ok": 200,
        "ko": 0
    },
    "minResponseTime": {
        "total": 20,
        "ok": 20,
        "ko": 0
    },
    "maxResponseTime": {
        "total": 5232,
        "ok": 5232,
        "ko": 0
    },
    "meanResponseTime": {
        "total": 524,
        "ok": 524,
        "ko": 0
    },
    "standardDeviation": {
        "total": 617,
        "ok": 617,
        "ko": 0
    },
    "percentiles1": {
        "total": 383,
        "ok": 383,
        "ko": 0
    },
    "percentiles2": {
        "total": 618,
        "ok": 618,
        "ko": 0
    },
    "percentiles3": {
        "total": 1172,
        "ok": 1172,
        "ko": 0
    },
    "percentiles4": {
        "total": 3380,
        "ok": 3380,
        "ko": 0
    },
    "group1": {
        "name": "t < 800 ms",
        "count": 169,
        "percentage": 85
    },
    "group2": {
        "name": "800 ms < t < 1200 ms",
        "count": 21,
        "percentage": 11
    },
    "group3": {
        "name": "t > 1200 ms",
        "count": 10,
        "percentage": 5
    },
    "group4": {
        "name": "failed",
        "count": 0,
        "percentage": 0
    },
    "meanNumberOfRequestsPerSecond": {
        "total": 1.1299435028248588,
        "ok": 1.1299435028248588,
        "ko": 0
    }
}
    },"req_request-132-2c1cc": {
        "type": "REQUEST",
        "name": "request_132",
"path": "request_132",
"pathFormatted": "req_request-132-2c1cc",
"stats": {
    "name": "request_132",
    "numberOfRequests": {
        "total": 200,
        "ok": 200,
        "ko": 0
    },
    "minResponseTime": {
        "total": 21,
        "ok": 21,
        "ko": 0
    },
    "maxResponseTime": {
        "total": 5232,
        "ok": 5232,
        "ko": 0
    },
    "meanResponseTime": {
        "total": 507,
        "ok": 507,
        "ko": 0
    },
    "standardDeviation": {
        "total": 526,
        "ok": 526,
        "ko": 0
    },
    "percentiles1": {
        "total": 382,
        "ok": 382,
        "ko": 0
    },
    "percentiles2": {
        "total": 619,
        "ok": 619,
        "ko": 0
    },
    "percentiles3": {
        "total": 1207,
        "ok": 1207,
        "ko": 0
    },
    "percentiles4": {
        "total": 2368,
        "ok": 2368,
        "ko": 0
    },
    "group1": {
        "name": "t < 800 ms",
        "count": 170,
        "percentage": 85
    },
    "group2": {
        "name": "800 ms < t < 1200 ms",
        "count": 19,
        "percentage": 10
    },
    "group3": {
        "name": "t > 1200 ms",
        "count": 11,
        "percentage": 6
    },
    "group4": {
        "name": "failed",
        "count": 0,
        "percentage": 0
    },
    "meanNumberOfRequestsPerSecond": {
        "total": 1.1299435028248588,
        "ok": 1.1299435028248588,
        "ko": 0
    }
}
    },"req_request-153-74659": {
        "type": "REQUEST",
        "name": "request_153",
"path": "request_153",
"pathFormatted": "req_request-153-74659",
"stats": {
    "name": "request_153",
    "numberOfRequests": {
        "total": 200,
        "ok": 200,
        "ko": 0
    },
    "minResponseTime": {
        "total": 19,
        "ok": 19,
        "ko": 0
    },
    "maxResponseTime": {
        "total": 2665,
        "ok": 2665,
        "ko": 0
    },
    "meanResponseTime": {
        "total": 486,
        "ok": 486,
        "ko": 0
    },
    "standardDeviation": {
        "total": 439,
        "ok": 439,
        "ko": 0
    },
    "percentiles1": {
        "total": 359,
        "ok": 359,
        "ko": 0
    },
    "percentiles2": {
        "total": 664,
        "ok": 664,
        "ko": 0
    },
    "percentiles3": {
        "total": 1257,
        "ok": 1257,
        "ko": 0
    },
    "percentiles4": {
        "total": 2335,
        "ok": 2335,
        "ko": 0
    },
    "group1": {
        "name": "t < 800 ms",
        "count": 170,
        "percentage": 85
    },
    "group2": {
        "name": "800 ms < t < 1200 ms",
        "count": 18,
        "percentage": 9
    },
    "group3": {
        "name": "t > 1200 ms",
        "count": 12,
        "percentage": 6
    },
    "group4": {
        "name": "failed",
        "count": 0,
        "percentage": 0
    },
    "meanNumberOfRequestsPerSecond": {
        "total": 1.1299435028248588,
        "ok": 1.1299435028248588,
        "ko": 0
    }
}
    },"req_request-154-9a47a": {
        "type": "REQUEST",
        "name": "request_154",
"path": "request_154",
"pathFormatted": "req_request-154-9a47a",
"stats": {
    "name": "request_154",
    "numberOfRequests": {
        "total": 200,
        "ok": 200,
        "ko": 0
    },
    "minResponseTime": {
        "total": 22,
        "ok": 22,
        "ko": 0
    },
    "maxResponseTime": {
        "total": 2783,
        "ok": 2783,
        "ko": 0
    },
    "meanResponseTime": {
        "total": 450,
        "ok": 450,
        "ko": 0
    },
    "standardDeviation": {
        "total": 417,
        "ok": 417,
        "ko": 0
    },
    "percentiles1": {
        "total": 329,
        "ok": 329,
        "ko": 0
    },
    "percentiles2": {
        "total": 604,
        "ok": 604,
        "ko": 0
    },
    "percentiles3": {
        "total": 1191,
        "ok": 1191,
        "ko": 0
    },
    "percentiles4": {
        "total": 2155,
        "ok": 2155,
        "ko": 0
    },
    "group1": {
        "name": "t < 800 ms",
        "count": 170,
        "percentage": 85
    },
    "group2": {
        "name": "800 ms < t < 1200 ms",
        "count": 20,
        "percentage": 10
    },
    "group3": {
        "name": "t > 1200 ms",
        "count": 10,
        "percentage": 5
    },
    "group4": {
        "name": "failed",
        "count": 0,
        "percentage": 0
    },
    "meanNumberOfRequestsPerSecond": {
        "total": 1.1299435028248588,
        "ok": 1.1299435028248588,
        "ko": 0
    }
}
    },"req_request-155-03639": {
        "type": "REQUEST",
        "name": "request_155",
"path": "request_155",
"pathFormatted": "req_request-155-03639",
"stats": {
    "name": "request_155",
    "numberOfRequests": {
        "total": 200,
        "ok": 200,
        "ko": 0
    },
    "minResponseTime": {
        "total": 21,
        "ok": 21,
        "ko": 0
    },
    "maxResponseTime": {
        "total": 2380,
        "ok": 2380,
        "ko": 0
    },
    "meanResponseTime": {
        "total": 439,
        "ok": 439,
        "ko": 0
    },
    "standardDeviation": {
        "total": 376,
        "ok": 376,
        "ko": 0
    },
    "percentiles1": {
        "total": 331,
        "ok": 331,
        "ko": 0
    },
    "percentiles2": {
        "total": 621,
        "ok": 621,
        "ko": 0
    },
    "percentiles3": {
        "total": 1227,
        "ok": 1227,
        "ko": 0
    },
    "percentiles4": {
        "total": 1582,
        "ok": 1582,
        "ko": 0
    },
    "group1": {
        "name": "t < 800 ms",
        "count": 172,
        "percentage": 86
    },
    "group2": {
        "name": "800 ms < t < 1200 ms",
        "count": 17,
        "percentage": 9
    },
    "group3": {
        "name": "t > 1200 ms",
        "count": 11,
        "percentage": 6
    },
    "group4": {
        "name": "failed",
        "count": 0,
        "percentage": 0
    },
    "meanNumberOfRequestsPerSecond": {
        "total": 1.1299435028248588,
        "ok": 1.1299435028248588,
        "ko": 0
    }
}
    },"req_request-160-5e678": {
        "type": "REQUEST",
        "name": "request_160",
"path": "request_160",
"pathFormatted": "req_request-160-5e678",
"stats": {
    "name": "request_160",
    "numberOfRequests": {
        "total": 200,
        "ok": 200,
        "ko": 0
    },
    "minResponseTime": {
        "total": 19,
        "ok": 19,
        "ko": 0
    },
    "maxResponseTime": {
        "total": 5049,
        "ok": 5049,
        "ko": 0
    },
    "meanResponseTime": {
        "total": 422,
        "ok": 422,
        "ko": 0
    },
    "standardDeviation": {
        "total": 562,
        "ok": 562,
        "ko": 0
    },
    "percentiles1": {
        "total": 282,
        "ok": 282,
        "ko": 0
    },
    "percentiles2": {
        "total": 524,
        "ok": 524,
        "ko": 0
    },
    "percentiles3": {
        "total": 1195,
        "ok": 1195,
        "ko": 0
    },
    "percentiles4": {
        "total": 2270,
        "ok": 2270,
        "ko": 0
    },
    "group1": {
        "name": "t < 800 ms",
        "count": 176,
        "percentage": 88
    },
    "group2": {
        "name": "800 ms < t < 1200 ms",
        "count": 14,
        "percentage": 7
    },
    "group3": {
        "name": "t > 1200 ms",
        "count": 10,
        "percentage": 5
    },
    "group4": {
        "name": "failed",
        "count": 0,
        "percentage": 0
    },
    "meanNumberOfRequestsPerSecond": {
        "total": 1.1299435028248588,
        "ok": 1.1299435028248588,
        "ko": 0
    }
}
    },"req_request-162-c14e8": {
        "type": "REQUEST",
        "name": "request_162",
"path": "request_162",
"pathFormatted": "req_request-162-c14e8",
"stats": {
    "name": "request_162",
    "numberOfRequests": {
        "total": 200,
        "ok": 200,
        "ko": 0
    },
    "minResponseTime": {
        "total": 19,
        "ok": 19,
        "ko": 0
    },
    "maxResponseTime": {
        "total": 3379,
        "ok": 3379,
        "ko": 0
    },
    "meanResponseTime": {
        "total": 359,
        "ok": 359,
        "ko": 0
    },
    "standardDeviation": {
        "total": 471,
        "ok": 471,
        "ko": 0
    },
    "percentiles1": {
        "total": 250,
        "ok": 250,
        "ko": 0
    },
    "percentiles2": {
        "total": 459,
        "ok": 459,
        "ko": 0
    },
    "percentiles3": {
        "total": 965,
        "ok": 965,
        "ko": 0
    },
    "percentiles4": {
        "total": 2954,
        "ok": 2954,
        "ko": 0
    },
    "group1": {
        "name": "t < 800 ms",
        "count": 187,
        "percentage": 94
    },
    "group2": {
        "name": "800 ms < t < 1200 ms",
        "count": 8,
        "percentage": 4
    },
    "group3": {
        "name": "t > 1200 ms",
        "count": 5,
        "percentage": 3
    },
    "group4": {
        "name": "failed",
        "count": 0,
        "percentage": 0
    },
    "meanNumberOfRequestsPerSecond": {
        "total": 1.1299435028248588,
        "ok": 1.1299435028248588,
        "ko": 0
    }
}
    },"req_request-161-c890c": {
        "type": "REQUEST",
        "name": "request_161",
"path": "request_161",
"pathFormatted": "req_request-161-c890c",
"stats": {
    "name": "request_161",
    "numberOfRequests": {
        "total": 200,
        "ok": 200,
        "ko": 0
    },
    "minResponseTime": {
        "total": 19,
        "ok": 19,
        "ko": 0
    },
    "maxResponseTime": {
        "total": 9053,
        "ok": 9053,
        "ko": 0
    },
    "meanResponseTime": {
        "total": 385,
        "ok": 385,
        "ko": 0
    },
    "standardDeviation": {
        "total": 776,
        "ok": 776,
        "ko": 0
    },
    "percentiles1": {
        "total": 235,
        "ok": 235,
        "ko": 0
    },
    "percentiles2": {
        "total": 458,
        "ok": 458,
        "ko": 0
    },
    "percentiles3": {
        "total": 957,
        "ok": 957,
        "ko": 0
    },
    "percentiles4": {
        "total": 2898,
        "ok": 2898,
        "ko": 0
    },
    "group1": {
        "name": "t < 800 ms",
        "count": 187,
        "percentage": 94
    },
    "group2": {
        "name": "800 ms < t < 1200 ms",
        "count": 8,
        "percentage": 4
    },
    "group3": {
        "name": "t > 1200 ms",
        "count": 5,
        "percentage": 3
    },
    "group4": {
        "name": "failed",
        "count": 0,
        "percentage": 0
    },
    "meanNumberOfRequestsPerSecond": {
        "total": 1.1299435028248588,
        "ok": 1.1299435028248588,
        "ko": 0
    }
}
    },"req_request-175-e44bb": {
        "type": "REQUEST",
        "name": "request_175",
"path": "request_175",
"pathFormatted": "req_request-175-e44bb",
"stats": {
    "name": "request_175",
    "numberOfRequests": {
        "total": 200,
        "ok": 200,
        "ko": 0
    },
    "minResponseTime": {
        "total": 19,
        "ok": 19,
        "ko": 0
    },
    "maxResponseTime": {
        "total": 5369,
        "ok": 5369,
        "ko": 0
    },
    "meanResponseTime": {
        "total": 324,
        "ok": 324,
        "ko": 0
    },
    "standardDeviation": {
        "total": 500,
        "ok": 500,
        "ko": 0
    },
    "percentiles1": {
        "total": 200,
        "ok": 200,
        "ko": 0
    },
    "percentiles2": {
        "total": 423,
        "ok": 423,
        "ko": 0
    },
    "percentiles3": {
        "total": 984,
        "ok": 984,
        "ko": 0
    },
    "percentiles4": {
        "total": 1694,
        "ok": 1694,
        "ko": 0
    },
    "group1": {
        "name": "t < 800 ms",
        "count": 187,
        "percentage": 94
    },
    "group2": {
        "name": "800 ms < t < 1200 ms",
        "count": 10,
        "percentage": 5
    },
    "group3": {
        "name": "t > 1200 ms",
        "count": 3,
        "percentage": 2
    },
    "group4": {
        "name": "failed",
        "count": 0,
        "percentage": 0
    },
    "meanNumberOfRequestsPerSecond": {
        "total": 1.1299435028248588,
        "ok": 1.1299435028248588,
        "ko": 0
    }
}
    },"req_request-176-5bec6": {
        "type": "REQUEST",
        "name": "request_176",
"path": "request_176",
"pathFormatted": "req_request-176-5bec6",
"stats": {
    "name": "request_176",
    "numberOfRequests": {
        "total": 200,
        "ok": 200,
        "ko": 0
    },
    "minResponseTime": {
        "total": 17,
        "ok": 17,
        "ko": 0
    },
    "maxResponseTime": {
        "total": 2045,
        "ok": 2045,
        "ko": 0
    },
    "meanResponseTime": {
        "total": 251,
        "ok": 251,
        "ko": 0
    },
    "standardDeviation": {
        "total": 254,
        "ok": 254,
        "ko": 0
    },
    "percentiles1": {
        "total": 190,
        "ok": 190,
        "ko": 0
    },
    "percentiles2": {
        "total": 327,
        "ok": 327,
        "ko": 0
    },
    "percentiles3": {
        "total": 713,
        "ok": 713,
        "ko": 0
    },
    "percentiles4": {
        "total": 935,
        "ok": 935,
        "ko": 0
    },
    "group1": {
        "name": "t < 800 ms",
        "count": 194,
        "percentage": 97
    },
    "group2": {
        "name": "800 ms < t < 1200 ms",
        "count": 5,
        "percentage": 3
    },
    "group3": {
        "name": "t > 1200 ms",
        "count": 1,
        "percentage": 1
    },
    "group4": {
        "name": "failed",
        "count": 0,
        "percentage": 0
    },
    "meanNumberOfRequestsPerSecond": {
        "total": 1.1299435028248588,
        "ok": 1.1299435028248588,
        "ko": 0
    }
}
    },"req_request-177-2cc1d": {
        "type": "REQUEST",
        "name": "request_177",
"path": "request_177",
"pathFormatted": "req_request-177-2cc1d",
"stats": {
    "name": "request_177",
    "numberOfRequests": {
        "total": 200,
        "ok": 200,
        "ko": 0
    },
    "minResponseTime": {
        "total": 20,
        "ok": 20,
        "ko": 0
    },
    "maxResponseTime": {
        "total": 1891,
        "ok": 1891,
        "ko": 0
    },
    "meanResponseTime": {
        "total": 253,
        "ok": 253,
        "ko": 0
    },
    "standardDeviation": {
        "total": 247,
        "ok": 247,
        "ko": 0
    },
    "percentiles1": {
        "total": 192,
        "ok": 192,
        "ko": 0
    },
    "percentiles2": {
        "total": 341,
        "ok": 341,
        "ko": 0
    },
    "percentiles3": {
        "total": 713,
        "ok": 713,
        "ko": 0
    },
    "percentiles4": {
        "total": 922,
        "ok": 922,
        "ko": 0
    },
    "group1": {
        "name": "t < 800 ms",
        "count": 193,
        "percentage": 97
    },
    "group2": {
        "name": "800 ms < t < 1200 ms",
        "count": 6,
        "percentage": 3
    },
    "group3": {
        "name": "t > 1200 ms",
        "count": 1,
        "percentage": 1
    },
    "group4": {
        "name": "failed",
        "count": 0,
        "percentage": 0
    },
    "meanNumberOfRequestsPerSecond": {
        "total": 1.1299435028248588,
        "ok": 1.1299435028248588,
        "ko": 0
    }
}
    }
}

}